hexacontroller_sc_server/Hexaboard.py
hexacontroller_sc_server/ROCv3.py
hexacontroller_sc_server/__init__.py
hexacontroller_sc_server/__main__.py
hexacontroller_sc_server/hexactrl_io.py
hexacontroller_sc_server/i2c_utilities.py
hexacontroller_sc_server/mock_io.py
hexacontroller_sc_server/server.py
hexacontroller_sc_server/tests.py
hexacontroller_sc_server/regmaps/HGCROC3_I2C_params_regmap.csv
hexacontroller_sc_server/regmaps/HGCROC3_sipm_I2C_params_regmap.csv
hexacontroller_sc_server/regmaps/HGCROCv2_I2C_params_regmap.csv
hexacontroller_sc_server/regmaps/HGCROCv2_sipm_I2C_params_regmap.csv
hexacontroller_sc_server-1.2.3.dist-info/METADATA
hexacontroller_sc_server-1.2.3.dist-info/WHEEL
hexacontroller_sc_server-1.2.3.dist-info/entry_points.txt
hexacontroller_sc_server-1.2.3.dist-info/top_level.txt
hexacontroller_sc_server-1.2.3.dist-info/RECORD
