Metadata-Version: 2.1
Name: hexacontroller-sc-server
Version: 1.2.3
Summary: A prospective zmq-i2c server replacement
Home-page: https://gitlab.cern.ch/albecker/hgcroc-tools.git
Author: Alex Becker, Jonathan Trieloff
Author-email: j.trieloff@cern.ch
License: MIT
Classifier: License :: OSI Approved :: MIT License
Classifier: Programming Language :: Python :: 3
Classifier: Programming Language :: Python :: 3.7
Requires-Dist: alabaster
Requires-Dist: attrs
Requires-Dist: Babel
Requires-Dist: certifi
Requires-Dist: charset-normalizer
Requires-Dist: click
Requires-Dist: contextlib2
Requires-Dist: docutils
Requires-Dist: gpiod
Requires-Dist: guzzle-sphinx-theme
Requires-Dist: hgcal-utilities
Requires-Dist: idna
Requires-Dist: imagesize
Requires-Dist: iniconfig
Requires-Dist: Jinja2
Requires-Dist: MarkupSafe
Requires-Dist: numpy
Requires-Dist: packaging
Requires-Dist: pandas
Requires-Dist: pathlib2
Requires-Dist: pluggy
Requires-Dist: py
Requires-Dist: Pygments
Requires-Dist: pyparsing
Requires-Dist: pytest
Requires-Dist: python-dateutil
Requires-Dist: pytz
Requires-Dist: PyYAML
Requires-Dist: pyzmq
Requires-Dist: requests
Requires-Dist: schema
Requires-Dist: six
Requires-Dist: smbus2
Requires-Dist: snowballstemmer
Requires-Dist: Sphinx
Requires-Dist: sphinxcontrib-applehelp
Requires-Dist: sphinxcontrib-devhelp
Requires-Dist: sphinxcontrib-htmlhelp
Requires-Dist: sphinxcontrib-jsmath
Requires-Dist: sphinxcontrib-qthelp
Requires-Dist: sphinxcontrib-serializinghtml
Requires-Dist: tomli
Requires-Dist: urllib3
Requires-Dist: zmq
